mmar_flame/__init__.py
mmar_flame/moderator.py
mmar_flame-1.0.0.dist-info/licenses/LICENSE
mmar_flame-1.0.0.dist-info/WHEEL
mmar_flame-1.0.0.dist-info/METADATA
mmar_flame-1.0.0.dist-info/RECORD
