Metadata-Version: 2.4
Name: mmar-flame
Version: 1.0.0
Summary: Flexible LLM-Assisted Moderation Engine: https://arxiv.org/abs/2502.09175
Keywords: 
Author: Ilia Kopanichuk
Author-email: Ilia Kopanichuk <kopanichuk@airi.net>
License-Expression: MIT
License-File: LICENSE
Classifier: Development Status :: 4 - Beta
Classifier: Intended Audience :: Developers
Classifier: Programming Language :: Python
Classifier: Programming Language :: Python :: 3
Classifier: Programming Language :: Python :: 3 :: Only
Classifier: Programming Language :: Python :: 3.12
Classifier: Programming Language :: Python :: 3.13
Classifier: Programming Language :: Python :: 3.14
Classifier: Topic :: Documentation
Classifier: Topic :: Software Development
Classifier: Topic :: Utilities
Classifier: Typing :: Typed
Requires-Dist: loguru>=0.7.3
Requires-Dist: nltk>=3.9.1
Requires-Dist: pydantic~=2.11.7
Requires-Dist: pymorphy3>=2.0.4
Requires-Dist: tqdm~=4.67.0
Requires-Dist: transliterate>=1.10.2
Requires-Dist: types-tqdm~=4.67.0
Requires-Dist: ujson>=5.11.0
Requires-Python: >=3.12
